multidimensional_wilcoxon_mann_whitney/__init__.py
multidimensional_wilcoxon_mann_whitney/multidimensional_ranksum.py
multidimensional_wilcoxon_mann_whitney-0.0.1.post7.dist-info/METADATA
multidimensional_wilcoxon_mann_whitney-0.0.1.post7.dist-info/WHEEL
multidimensional_wilcoxon_mann_whitney-0.0.1.post7.dist-info/RECORD
